setup.py
SHICTHRSCSVLoader/__init__.py
SHICTHRSCSVLoader.egg-info/PKG-INFO
SHICTHRSCSVLoader.egg-info/SOURCES.txt
SHICTHRSCSVLoader.egg-info/dependency_links.txt
SHICTHRSCSVLoader.egg-info/not-zip-safe
SHICTHRSCSVLoader.egg-info/requires.txt
SHICTHRSCSVLoader.egg-info/top_level.txt
SHICTHRSCSVLoader/utils/SHRCSVLoader_insert_csv_file.py
SHICTHRSCSVLoader/utils/SHRCSVLoader_read_csv_file.py
SHICTHRSCSVLoader/utils/SHRCSVLoader_write_csv_file.py
SHICTHRSCSVLoader/utils/__init__.py