Metadata-Version: 2.4
Name: SHICTHRSCSVLoader
Version: 1.5.0
Summary: SHICTHRS CSV file io system
Home-page: https://github.com/JNTMTMTM/SHICTHRS_CSVLoader
Author: SHICTHRS
Author-email: contact@shicthrs.com
License: GPL-3.0
Requires-Dist: colorama==0.4.6
Requires-Dist: pandas==2.3.3
Dynamic: author
Dynamic: author-email
Dynamic: home-page
Dynamic: license
Dynamic: requires-dist
Dynamic: summary
